Workbook

Sheet Mode d'emploi
A1: KIT PUB LIMO — Meta Ads + Google Ads
A2: Le bras droit du conseiller immo · Essai 14 jours sans CB · Dès 49 €/mois
A4: Onglet | B4: À quoi il sert | C4: Quand l'utiliser
A5: Checklist | B5: Tout ce qu'il faut installer AVANT de dépenser 1 € | C5: Jour 1, une seule fois
A6: Hypothèses | B6: Ton prix, ta rétention, ton taux essai→payant → calcule ton coût max par essai | C6: Jour 1, puis chaque mois avec tes vrais chiffres
A7: Pilotage | B7: Tableau hebdo : tu tapes 8 chiffres par canal, il calcule tout et te dit quoi faire | C7: Chaque lundi, 10 min
A8: Meta - Annonces | B8: Textes prêts à coller pour chaque vidéo + lien avec UTM | C8: À la création des pubs
A9: Google - Annonces | B9: 15 titres + 4 descriptions + extensions (longueurs vérifiées) | C9: À la création de la campagne Search
A10: Mots-clés | B10: Mots-clés par groupe d'annonces + CPC max de départ | C10: Création campagne, puis revue hebdo
A11: Exclusions | B11: Mots-clés négatifs à ajouter dès le départ | C11: Création campagne
A13: Légende des couleurs
A14: Texte bleu sur fond jaune | B14: =cellule à remplir par toi (chiffres de tes comptes pub / de l'app)
A15: Texte noir | B15: =formule calculée automatiquement, ne pas toucher
A17: Les chiffres de départ (prix, rétention, taux) sont des hypothèses à remplacer par tes vrais chiffres dès que tu les as.

Sheet Checklist
A1: Checklist d'installation — à faire avant de lancer
A3: # | B3: Domaine | C3: Étape (où / comment) | D3: Pourquoi | E3: Statut
A4: 1 | B4: Landing page | C4: Remplacer toute mention « 1 mois » par « 14 jours, sans carte bancaire » (titre, bouton, FAQ) | D4: Même promesse pub = page, sinon conversion en chute et refus Meta possible | E4: À faire
A5: 2 | B5: Landing page | C5: Bouton « Réserver une démo de 15 min » visible + formulaire d'essai en moins de 3 champs | D5: Chaque champ en plus fait perdre des inscrits | E5: À faire
A6: 3 | B6: Landing page | C6: Mentions légales, politique de confidentialité et CGV accessibles en bas de page | D6: Obligatoire + vérifié par Meta et Google | E6: À faire
A7: 4 | B7: Cookies | C7: Bandeau de consentement compatible Consent Mode v2 (ex. Axeptio, Didomi, Cookiebot) | D7: Obligatoire en Europe (RGPD/CNIL) ; sans lui Google limite le suivi | E7: À faire
A8: 5 | B8: Meta | C8: Créer le Business Manager (business.facebook.com), y rattacher la Page LIMO + le compte Instagram | D8: Base de tout | E8: À faire
A9: 6 | B9: Meta | C9: Activer la double authentification sur ton compte et le Business Manager | D9: Évite le piratage du compte pub (fréquent) | E9: À faire
A10: 7 | B10: Meta | C10: Créer le compte publicitaire, devise EUR, fuseau Europe/Paris, moyen de paiement | D10: Fuseau et devise ne se changent plus ensuite | E10: À faire
A11: 8 | B11: Meta | C11: Vérifier le domaine leadengineai.fr (Paramètres de l'entreprise → Sécurité de la marque → Domaines) | D11: Nécessaire pour configurer les conversions | E11: À faire
A12: 9 | B12: Meta | C12: Installer le Pixel Meta sur app.leadengineai.fr (toutes les pages) | D12: Mesure les visites et conversions | E12: À faire
A13: 10 | B13: Meta | C13: Activer la Conversions API (via Gestionnaire d'événements, intégration partenaire ou serveur) | D13: Récupère les conversions perdues (iPhone, bloqueurs) | E13: À faire
A14: 11 | B14: Meta | C14: Événements : Lead (démo réservée), CompleteRegistration (essai démarré), Subscribe (passage payant) | D14: C'est ce que l'algorithme va optimiser | E14: À faire
A15: 12 | B15: Meta | C15: Tester les événements avec l'outil « Tester les événements » du Gestionnaire d'événements | D15: Ne jamais lancer sans voir les événements remonter | E15: À faire
... A24: 21 | B24: Conformité | C24: Photos de clients (film signatures) : accord écrit des personnes, même floutées | D24: Droit à l'image | E24: À faire
B26: Avancement | C26: =COUNTIF(E4:E24,"Fait")/COUNTA(E4:E24)

Sheet Hypothèses
A1: Hypothèses économiques
A3: Paramètre | B3: Valeur | C3: Note
A4: Prix de l'abonnement (€/mois) | B4: 49 | C4: Prix d'entrée LIMO (« dès 49 €/mois »). Source : Thomy.
A5: Durée moyenne d'abonnement (mois) | B5: 12 | C5: HYPOTHÈSE — à remplacer par ta rétention réelle après 3-6 mois.
A6: Taux essai → payant | B6: 0.25 | C6: HYPOTHÈSE — à remplacer par ton taux réel (onglet Pilotage).
A7: Mois d'abonnement acceptés pour payer l'acquisition | B7: 3 | C7: Règle de prudence : on récupère sa dépense pub en 3 mois.
A8: Résultats calculés
A9: Valeur d'un client (€) | B9: =B4*B5 | C9: Prix × durée moyenne
A10: Coût d'acquisition max par client payant (€) | B10: =B4*B7 | C10: Ce que tu peux payer pour 1 client
A11: Coût max par essai démarré (€) | B11: =B10*B6 | C11: KPI n°1 : à surveiller chaque semaine
A12: Seuil « à couper » d'une pub sans essai (€ dépensés) | B12: =B11*2 | C12: Une pub qui a dépensé ça sans aucun essai → on l'arrête

Sheet Pilotage
A1: Pilotage hebdomadaire — remplis les colonnes jaunes chaque lundi
A3: Semaine (lundi) | B3: Canal | C3: Dépense (€) | D3: Impressions | E3: Vues 3 s (Meta) | F3: Clics lien | G3: Essais démarrés | H3: Démos réservées | I3: Clients payants | J3: CPM (€) | K3: Taux de hook | L3: CTR | M3: Coût par clic (€) | N3: Taux clic → essai | O3: Coût par essai (€) | P3: Coût par client (€) | Q3: Verdict
A4: 46300 | B4: Meta | C4: 175 | D4: 21000 | E4: 6300 | F4: 230 | G4: 6 | H4: 2 | I4: 1 | J4: =IF(D4>0,C4/D4*1000,"") | K4: =IF(AND(B4="Meta",D4>0,E4<>""),E4/D4,"") | L4: =IF(D4>0,F4/D4,"") | M4: =IF(F4>0,C4/F4,"") | N4: =IF(F4>0,G4/F4,"") | O4: =IF(G4>0,C4/G4,"") | P4: =IF(I4>0,C4/I4,"") | Q4: =IF(C4="","",IF(G4=0,IF(C4>='Hypothèses'!$B$12,"🔴 Aucun essai : changer de visuel/angle","⏳ Trop tôt, laisser tourner"),IF(O4<='Hypothèses'!$B$11*0.8,"🟢 Rentable : +20 % de budget",IF(O4<='Hypothèses'!$B$11,"🟡 Correct : tester 2 nouveaux visuels","🔴 Trop cher : couper les pires pubs"))))
A5: 46300 | B5: Google | C5: 70 | D5: 1400 | F5: 48 | G5: 3 | H5: 1 | I5: 0 | J5: =IF(D5>0,C5/D5*1000,"") | K5: =IF(AND(B5="Meta",D5>0,E5<>""),E5/D5,"") | L5: =IF(D5>0,F5/D5,"") | M5: =IF(F5>0,C5/F5,"") | N5: =IF(F5>0,G5/F5,"") | O5: =IF(G5>0,C5/G5,"") | P5: =IF(I5>0,C5/I5,"") | Q5: =IF(C5="","",IF(G5=0,IF(C5>='Hypothèses'!$B$12,"🔴 Aucun essai : changer de visuel/angle","⏳ Trop tôt, laisser tourner"),IF(O5<='Hypothèses'!$B$11*0.8,"🟢 Rentable : +20 % de budget",IF(O5<='Hypothèses'!$B$11,"🟡 Correct : tester 2 nouveaux visuels","🔴 Trop cher : couper les pires pubs"))))
A6: 46307 | B6: Meta | J6: =IF(D6>0,C6/D6*1000,"") | K6: =IF(AND(B6="Meta",D6>0,E6<>""),E6/D6,"") | L6: =IF(D6>0,F6/D6,"") | M6: =IF(F6>0,C6/F6,"") | N6: =IF(F6>0,G6/F6,"") | O6: =IF(G6>0,C6/G6,"") | P6: =IF(I6>0,C6/I6,"") | Q6: =IF(C6="","",IF(G6=0,IF(C6>='Hypothèses'!$B$12,"🔴 Aucun essai : changer de visuel/angle","⏳ Trop tôt, laisser tourner"),IF(O6<='Hypothèses'!$B$11*0.8,"🟢 Rentable : +20 % de budget",IF(O6<='Hypothèses'!$B$11,"🟡 Correct : tester 2 nouveaux visuels","🔴 Trop cher : couper les pires pubs"))))
A7: 46307 | B7: Google | J7: =IF(D7>0,C7/D7*1000,"") | K7: =IF(AND(B7="Meta",D7>0,E7<>""),E7/D7,"") | L7: =IF(D7>0,F7/D7,"") | M7: =IF(F7>0,C7/F7,"") | N7: =IF(F7>0,G7/F7,"") | O7: =IF(G7>0,C7/G7,"") | P7: =IF(I7>0,C7/I7,"") | Q7: =IF(C7="","",IF(G7=0,IF(C7>='Hypothèses'!$B$12,"🔴 Aucun essai : changer de visuel/angle","⏳ Trop tôt, laisser tourner"),IF(O7<='Hypothèses'!$B$11*0.8,"🟢 Rentable : +20 % de budget",IF(O7<='Hypothèses'!$B$11,"🟡 Correct : tester 2 nouveaux visuels","🔴 Trop cher : couper les pires pubs"))))
A8: 46314 | B8: Meta | J8: =IF(D8>0,C8/D8*1000,"") | K8: =IF(AND(B8="Meta",D8>0,E8<>""),E8/D8,"") | L8: =IF(D8>0,F8/D8,"") | M8: =IF(F8>0,C8/F8,"") | N8: =IF(F8>0,G8/F8,"") | O8: =IF(G8>0,C8/G8,"") | P8: =IF(I8>0,C8/I8,"") | Q8: =IF(C8="","",IF(G8=0,IF(C8>='Hypothèses'!$B$12,"🔴 Aucun essai : changer de visuel/angle","⏳ Trop tôt, laisser tourner"),IF(O8<='Hypothèses'!$B$11*0.8,"🟢 Rentable : +20 % de budget",IF(O8<='Hypothèses'!$B$11,"🟡 Correct : tester 2 nouveaux visuels","🔴 Trop cher : couper les pires pubs"))))
A9: 46314 | B9: Google | J9: =IF(D9>0,C9/D9*1000,"") | K9: =IF(AND(B9="Meta",D9>0,E9<>""),E9/D9,"") | L9: =IF(D9>0,F9/D9,"") | M9: =IF(F9>0,C9/F9,"") | N9: =IF(F9>0,G9/F9,"") | O9: =IF(G9>0,C9/G9,"") | P9: =IF(I9>0,C9/I9,"") | Q9: =IF(C9="","",IF(G9=0,IF(C9>='Hypothèses'!$B$12,"🔴 Aucun essai : changer de visuel/angle","⏳ Trop tôt, laisser tourner"),IF(O9<='Hypothèses'!$B$11*0.8,"🟢 Rentable : +20 % de budget",IF(O9<='Hypothèses'!$B$11,"🟡 Correct : tester 2 nouveaux visuels","🔴 Trop cher : couper les pires pubs"))))
A10: 46321 | B10: Meta | J10: =IF(D10>0,C10/D10*1000,"") | K10: =IF(AND(B10="Meta",D10>0,E10<>""),E10/D10,"") | L10: =IF(D10>0,F10/D10,"") | M10: =IF(F10>0,C10/F10,"") | N10: =IF(F10>0,G10/F10,"") | O10: =IF(G10>0,C10/G10,"") | P10: =IF(I10>0,C10/I10,"") | Q10: =IF(C10="","",IF(G10=0,IF(C10>='Hypothèses'!$B$12,"🔴 Aucun essai : changer de visuel/angle","⏳ Trop tôt, laisser tourner"),IF(O10<='Hypothèses'!$B$11*0.8,"🟢 Rentable : +20 % de budget",IF(O10<='Hypothèses'!$B$11,"🟡 Correct : tester 2 nouveaux visuels","🔴 Trop cher : couper les pires pubs"))))
A11: 46321 | B11: Google | J11: =IF(D11>0,C11/D11*1000,"") | K11: =IF(AND(B11="Meta",D11>0,E11<>""),E11/D11,"") | L11: =IF(D11>0,F11/D11,"") | M11: =IF(F11>0,C11/F11,"") | N11: =IF(F11>0,G11/F11,"") | O11: =IF(G11>0,C11/G11,"") | P11: =IF(I11>0,C11/I11,"") | Q11: =IF(C11="","",IF(G11=0,IF(C11>='Hypothèses'!$B$12,"🔴 Aucun essai : changer de visuel/angle","⏳ Trop tôt, laisser tourner"),IF(O11<='Hypothèses'!$B$11*0.8,"🟢 Rentable : +20 % de budget",IF(O11<='Hypothèses'!$B$11,"🟡 Correct : tester 2 nouveaux visuels","🔴 Trop cher : couper les pires pubs"))))
A12: 46328 | B12: Meta | J12: =IF(D12>0,C12/D12*1000,"") | K12: =IF(AND(B12="Meta",D12>0,E12<>""),E12/D12,"") | L12: =IF(D12>0,F12/D12,"") | M12: =IF(F12>0,C12/F12,"") | N12: =IF(F12>0,G12/F12,"") | O12: =IF(G12>0,C12/G12,"") | P12: =IF(I12>0,C12/I12,"") | Q12: =IF(C12="","",IF(G12=0,IF(C12>='Hypothèses'!$B$12,"🔴 Aucun essai : changer de visuel/angle","⏳ Trop tôt, laisser tourner"),IF(O12<='Hypothèses'!$B$11*0.8,"🟢 Rentable : +20 % de budget",IF(O12<='Hypothèses'!$B$11,"🟡 Correct : tester 2 nouveaux visuels","🔴 Trop cher : couper les pires pubs"))))
A13: 46328 | B13: Google | J13: =IF(D13>0,C13/D13*1000,"") | K13: =IF(AND(B13="Meta",D13>0,E13<>""),E13/D13,"") | L13: =IF(D13>0,F13/D13,"") | M13: =IF(F13>0,C13/F13,"") | N13: =IF(F13>0,G13/F13,"") | O13: =IF(G13>0,C13/G13,"") | P13: =IF(I13>0,C13/I13,"") | Q13: =IF(C13="","",IF(G13=0,IF(C13>='Hypothèses'!$B$12,"🔴 Aucun essai : changer de visuel/angle","⏳ Trop tôt, laisser tourner"),IF(O13<='Hypothèses'!$B$11*0.8,"🟢 Rentable : +20 % de budget",IF(O13<='Hypothèses'!$B$11,"🟡 Correct : tester 2 nouveaux visuels","🔴 Trop cher : couper les pires pubs"))))
A14: 46335 | B14: Meta | J14: =IF(D14>0,C14/D14*1000,"") | K14: =IF(AND(B14="Meta",D14>0,E14<>""),E14/D14,"") | L14: =IF(D14>0,F14/D14,"") | M14: =IF(F14>0,C14/F14,"") | N14: =IF(F14>0,G14/F14,"") | O14: =IF(G14>0,C14/G14,"") | P14: =IF(I14>0,C14/I14,"") | Q14: =IF(C14="","",IF(G14=0,IF(C14>='Hypothèses'!$B$12,"🔴 Aucun essai : changer de visuel/angle","⏳ Trop tôt, laisser tourner"),IF(O14<='Hypothèses'!$B$11*0.8,"🟢 Rentable : +20 % de budget",IF(O14<='Hypothèses'!$B$11,"🟡 Correct : tester 2 nouveaux visuels","🔴 Trop cher : couper les pires pubs"))))
A15: 46335 | B15: Google | J15: =IF(D15>0,C15/D15*1000,"") | K15: =IF(AND(B15="Meta",D15>0,E15<>""),E15/D15,"") | L15: =IF(D15>0,F15/D15,"") | M15: =IF(F15>0,C15/F15,"") | N15: =IF(F15>0,G15/F15,"") | O15: =IF(G15>0,C15/G15,"") | P15: =IF(I15>0,C15/I15,"") | Q15: =IF(C15="","",IF(G15=0,IF(C15>='Hypothèses'!$B$12,"🔴 Aucun essai : changer de visuel/angle","⏳ Trop tôt, laisser tourner"),IF(O15<='Hypothèses'!$B$11*0.8,"🟢 Rentable : +20 % de budget",IF(O15<='Hypothèses'!$B$11,"🟡 Correct : tester 2 nouveaux visuels","🔴 Trop cher : couper les pires pubs"))))
A16: 46342 | B16: Meta | J16: =IF(D16>0,C16/D16*1000,"") | K16: =IF(AND(B16="Meta",D16>0,E16<>""),E16/D16,"") | L16: =IF(D16>0,F16/D16,"") | M16: =IF(F16>0,C16/F16,"") | N16: =IF(F16>0,G16/F16,"") | O16: =IF(G16>0,C16/G16,"") | P16: =IF(I16>0,C16/I16,"") | Q16: =IF(C16="","",IF(G16=0,IF(C16>='Hypothèses'!$B$12,"🔴 Aucun essai : changer de visuel/angle","⏳ Trop tôt, laisser tourner"),IF(O16<='Hypothèses'!$B$11*0.8,"🟢 Rentable : +20 % de budget",IF(O16<='Hypothèses'!$B$11,"🟡 Correct : tester 2 nouveaux visuels","🔴 Trop cher : couper les pires pubs"))))
A17: 46342 | B17: Google | J17: =IF(D17>0,C17/D17*1000,"") | K17: =IF(AND(B17="Meta",D17>0,E17<>""),E17/D17,"") | L17: =IF(D17>0,F17/D17,"") | M17: =IF(F17>0,C17/F17,"") | N17: =IF(F17>0,G17/F17,"") | O17: =IF(G17>0,C17/G17,"") | P17: =IF(I17>0,C17/I17,"") | Q17: =IF(C17="","",IF(G17=0,IF(C17>='Hypothèses'!$B$12,"🔴 Aucun essai : changer de visuel/angle","⏳ Trop tôt, laisser tourner"),IF(O17<='Hypothèses'!$B$11*0.8,"🟢 Rentable : +20 % de budget",IF(O17<='Hypothèses'!$B$11,"🟡 Correct : tester 2 nouveaux visuels","🔴 Trop cher : couper les pires pubs"))))
... A29: 46384 | B29: Google | J29: =IF(D29>0,C29/D29*1000,"") | K29: =IF(AND(B29="Meta",D29>0,E29<>""),E29/D29,"") | L29: =IF(D29>0,F29/D29,"") | M29: =IF(F29>0,C29/F29,"") | N29: =IF(F29>0,G29/F29,"") | O29: =IF(G29>0,C29/G29,"") | P29: =IF(I29>0,C29/I29,"") | Q29: =IF(C29="","",IF(G29=0,IF(C29>='Hypothèses'!$B$12,"🔴 Aucun essai : changer de visuel/angle","⏳ Trop tôt, laisser tourner"),IF(O29<='Hypothèses'!$B$11*0.8,"🟢 Rentable : +20 % de budget",IF(O29<='Hypothèses'!$B$11,"🟡 Correct : tester 2 nouveaux visuels","🔴 Trop cher : couper les pires pubs"))))
A31: TOTAL | B31: Meta | C31: =SUMIFS(C4:C29,$B$4:$B$29,"Meta") | D31: =SUMIFS(D4:D29,$B$4:$B$29,"Meta") | E31: =SUMIFS(E4:E29,$B$4:$B$29,"Meta") | F31: =SUMIFS(F4:F29,$B$4:$B$29,"Meta") | G31: =SUMIFS(G4:G29,$B$4:$B$29,"Meta") | H31: =SUMIFS(H4:H29,$B$4:$B$29,"Meta") | I31: =SUMIFS(I4:I29,$B$4:$B$29,"Meta") | N31: =IF(F31>0,G31/F31,"") | O31: =IF(G31>0,C31/G31,"") | P31: =IF(I31>0,C31/I31,"")
B32: Google | C32: =SUMIFS(C4:C29,$B$4:$B$29,"Google") | D32: =SUMIFS(D4:D29,$B$4:$B$29,"Google") | E32: =SUMIFS(E4:E29,$B$4:$B$29,"Google") | F32: =SUMIFS(F4:F29,$B$4:$B$29,"Google") | G32: =SUMIFS(G4:G29,$B$4:$B$29,"Google") | H32: =SUMIFS(H4:H29,$B$4:$B$29,"Google") | I32: =SUMIFS(I4:I29,$B$4:$B$29,"Google") | N32: =IF(F32>0,G32/F32,"") | O32: =IF(G32>0,C32/G32,"") | P32: =IF(I32>0,C32/I32,"")
B33: Tous | C33: =SUM(C4:C29) | D33: =SUM(D4:D29) | E33: =SUM(E4:E29) | F33: =SUM(F4:F29) | G33: =SUM(G4:G29) | H33: =SUM(H4:H29) | I33: =SUM(I4:I29) | N33: =IF(F33>0,G33/F33,"") | O33: =IF(G33>0,C33/G33,"") | P33: =IF(I33>0,C33/I33,"")
A35: Taux essai → payant réel | C35: =IF(G33>0,I33/G33,"") | D35: → à reporter dans Hypothèses!B6 quand tu as au moins 20 essais
A36: Repères | C36: Taux de hook Meta : viser > 25 % · CTR lien Meta : viser > 1 % · CTR Google Search : viser > 4 %

Sheet Meta - Annonces
A1: Annonces Meta — textes prêts à coller (Facebook + Instagram)
A2: Rappel : 9:16 pour Reels/Stories + 4:5 pour le fil, dans la même annonce (« personnaliser le visuel par placement »).
A4: # | B4: Campagne | C4: Vidéo (fichier) | D4: Angle | E4: Texte principal | F4: Titre (≤ 40 car.) | G4: Description | H4: Bouton | I4: Lien avec UTM | J4: Nb car. titre
A5: 1 | B5: A – Acquisition | C5: voix/voix-03-surcharge.mp4 | D5: Surcharge (10 s) | E5: Conseiller immo, surchargé ? Appels manqués, relances oubliées, dossiers incomplets… LIMO s'en occupe pour toi. ✅ Relances automatiques ✅ Dossiers suivis jusqu'au notaire ✅ Estimations et annonces en quelques minutes Essai gratuit 14 jours, sans carte bancaire. | F5: LIMO, le bras droit du conseiller | G5: Dès 49 €/mois · sans engagement | H5: S'inscrire | I5: https://app.leadengineai.fr/?utm_source=meta&utm_medium=paid_social&utm_campaign=acquisition&utm_content=surcharge | J5: =LEN(F5)
A6: 2 | B6: A – Acquisition | C6: voix/voix-01-julien.mp4 | D6: Storytelling (59 s) | E6: Julien a fait une super estimation. Puis il a oublié de rappeler. Quelques jours plus tard, un autre panneau était sur la maison. Le mandat ne se perd pas pendant l'estimation. Il se perd APRÈS. LIMO garde le fil de chaque vendeur, chaque relance, chaque dossier. 👉 Réserve ta démo de 15 min. | F6: Ne perds plus un mandat par oubli | G6: Démo gratuite de 15 min | H6: Réserver | I6: https://app.leadengineai.fr/?utm_source=meta&utm_medium=paid_social&utm_campaign=acquisition&utm_content=julien | J6: =LEN(F6)
A7: 3 | B7: A – Acquisition | C7: voix/voix-02-regarde-ca.mp4 | D7: Démo produit (30 s) | E7: Conseiller immo, regarde ça 👀 Tu demandes « rappelle-moi le bien de M. et Mme T. » → LIMO te sort la fiche complète : documents, diagnostics, propriétaires, estimation. Et pendant ce temps, il relance tes acquéreurs et ton diagnostiqueur. Teste-le 14 jours, sans CB. | F7: Toute ton activité, au même endroit | G7: Essai gratuit 14 jours | H7: S'inscrire | I7: https://app.leadengineai.fr/?utm_source=meta&utm_medium=paid_social&utm_campaign=acquisition&utm_content=regarde-ca | J7: =LEN(F7)
A8: 4 | B8: A – Acquisition | C8: pubs-30s/LIMO-pub30-01-mandats-perdus-9x16.mp4 | D8: Perte de mandats (30 s) | E8: Combien de mandats as-tu perdus cette année… juste par manque de suivi ? LIMO relance tes vendeurs au bon moment, prépare tes estimations et garde tous tes dossiers à jour. Plus de temps sur le terrain, moins de temps sur l'administratif. Essai gratuit 14 jours, sans carte bancaire. | F8: Arrête de perdre des mandats | G8: Dès 49 €/mois | H8: S'inscrire | I8: https://app.leadengineai.fr/?utm_source=meta&utm_medium=paid_social&utm_campaign=acquisition&utm_content=mandats-perdus | J8: =LEN(F8)
A9: 5 | B9: A – Acquisition | C9: lifestyle/LIMO-life-02-pov-collegue-9x16.mp4 | D9: POV / humour | E9: POV : ton collègue a l'air moins débordé que toi… et il rentre plus tôt 😅 Son secret ? LIMO, le bras droit du conseiller immo. Relances, dossiers, annonces, estimations : c'est fait. 14 jours pour tester, sans CB. | F9: Son secret ? LIMO. | G9: Essai gratuit 14 jours | H9: En savoir plus | I9: https://app.leadengineai.fr/?utm_source=meta&utm_medium=paid_social&utm_campaign=acquisition&utm_content=pov-collegue | J9: =LEN(F9)
A10: 6 | B10: B – Relance | C10: signatures/sign-01-derriere-chaque-signature.mp4 | D10: Émotion (32 s) | E10: Le jour de la signature, on oublie tout le reste. Les appels du soir, les relances, les compromis, les diagnostics, les échanges avec le notaire… LIMO s'occupe du reste, pour un suivi ultra pro du mandat à la signature. 👉 Réserve ta démo de 15 min. | F10: Du mandat à la signature, sans oubli | G10: Démo gratuite de 15 min | H10: Réserver | I10: https://app.leadengineai.fr/?utm_source=meta&utm_medium=paid_social&utm_campaign=relance&utm_content=signatures | J10: =LEN(F10)
A11: 7 | B11: B – Relance | C11: cine/LIMO-cine-03-le-calcul-9x16.mp4 | D11: Rationnel (temps/argent) | E11: Fais le calcul : combien d'heures par semaine passes-tu sur l'administratif ? LIMO te les rend : relances, dossiers, annonces et estimations automatisés. Tu as déjà vu LIMO passer. Il ne te reste qu'à l'essayer : 14 jours, sans carte bancaire. | F11: Récupère tes heures d'admin | G11: Dès 49 €/mois · sans engagement | H11: S'inscrire | I11: https://app.leadengineai.fr/?utm_source=meta&utm_medium=paid_social&utm_campaign=relance&utm_content=le-calcul | J11: =LEN(F11)
B13: Réglages campagne A | E13: Objectif Ventes · Conversion : CompleteRegistration · France · 25-60 ans · ciblage large (Advantage+) · placements Advantage+ · 20 €/jour · ne rien modifier 5-7 jours
B14: Réglages campagne B | E14: Objectif Prospects · Conversion : Lead · Audiences : vidéo vue à 50 % + interactions Page/Insta + visiteurs site 30 j · EXCLURE les inscrits · 5-8 €/jour

Sheet Google - Annonces
A1: Google Ads Search — annonce responsive (RSA)
A2: Limites Google : titre ≤ 30 caractères · description ≤ 90 · chemin ≤ 15. La colonne « Nb car. » se colore en rouge si ça dépasse.
A4: Type | B4: Texte | C4: Nb car. | D4: Limite | E4: Épingler ?
A5: Titre | B5: LIMO, logiciel immo IA | C5: =LEN(B5) | D5: 30 | E5: Position 1
A6: Titre | B6: Le bras droit du conseiller | C6: =LEN(B6) | D6: 30
A7: Titre | B7: Essai gratuit 14 jours | C7: =LEN(B7) | D7: 30
A8: Titre | B8: Sans carte bancaire | C8: =LEN(B8) | D8: 30
A9: Titre | B9: Dès 49 €/mois | C9: =LEN(B9) | D9: 30
A10: Titre | B10: Relances vendeurs auto | C10: =LEN(B10) | D10: 30
A11: Titre | B11: Ne perdez plus un mandat | C11: =LEN(B11) | D11: 30
A12: Titre | B12: Dossiers suivis au notaire | C12: =LEN(B12) | D12: 30
A13: Titre | B13: Estimations en 2 minutes | C13: =LEN(B13) | D13: 30
A14: Titre | B14: Annonces rédigées pour vous | C14: =LEN(B14) | D14: 30
A15: Titre | B15: Fait pour les mandataires | C15: =LEN(B15) | D15: 30
A16: Titre | B16: Démo gratuite de 15 min | C16: =LEN(B16) | D16: 30
A17: Titre | B17: Plus de temps sur le terrain | C17: =LEN(B17) | D17: 30
... A25: Chemin d'URL | B25: conseiller-immo | C25: =LEN(B25) | D25: 15
A26: URL finale | B26: https://app.leadengineai.fr/?utm_source=google&utm_medium=cpc&utm_campaign=search-{_campagne}&utm_term={keyword} | E26: Remplace {_campagne} par un paramètre personnalisé ou le nom de campagne
A28: EXTENSIONS
A29: Type | B29: Texte | C29: Nb car. | D29: Limite | E29: Détail / URL
A30: Lien annexe | B30: Réserver une démo | C30: =LEN(B30) | D30: 25 | E30: Démo de 15 min en visio · https://app.leadengineai.fr/demo
A31: Lien annexe | B31: Tarifs | C31: =LEN(B31) | D31: 25 | E31: Dès 49 €/mois, sans engagement · https://app.leadengineai.fr/tarifs
A32: Lien annexe | B32: Fonctionnalités | C32: =LEN(B32) | D32: 25 | E32: Relances, dossiers, estimations · https://app.leadengineai.fr/fonctionnalites
A33: Lien annexe | B33: Essai gratuit 14 jours | C33: =LEN(B33) | D33: 25 | E33: Sans carte bancaire · https://app.leadengineai.fr/inscription
A34: Accroche | B34: Sans carte bancaire | C34: =LEN(B34) | D34: 25
A35: Accroche | B35: Sans engagement | C35: =LEN(B35) | D35: 25
A36: Accroche | B36: Support en français | C36: =LEN(B36) | D36: 25
A37: Accroche | B37: Prêt en 2 minutes | C37: =LEN(B37) | D37: 25
A38: Extrait structuré (Services) | B38: Relances, Estimations, Annonces, Dossiers, Suivi notaire | C38: — | D38: 25 | E38: Chaque valeur ≤ 25 car.
A40: ⚠️ | B40: Les pages /demo, /tarifs, /fonctionnalites, /inscription sont des suggestions : remplace-les par les vraies URL de ton site (ou la page d'accueil).

Sheet Mots-clés
A1: Mots-clés Google Search — campagne « LIMO – Search »
A2: [exact] = correspondance exacte · "expression" = expression. Commence avec ça, pas de requête large au départ.
A4: Groupe d'annonces | B4: Mot-clé | C4: Type | D4: CPC max départ (€) | E4: Statut
A5: Logiciel métier | B5: logiciel agent immobilier | C5: Exact | D5: 2 | E5: Actif
A6: Logiciel métier | B6: logiciel agent immobilier | C6: Expression | D6: 2 | E6: Actif
A7: Logiciel métier | B7: logiciel conseiller immobilier | C7: Exact | D7: 2 | E7: Actif
A8: Logiciel métier | B8: logiciel conseiller immobilier | C8: Expression | D8: 2 | E8: Actif
A9: Logiciel métier | B9: logiciel mandataire immobilier | C9: Exact | D9: 2 | E9: Actif
A10: Logiciel métier | B10: logiciel mandataire immobilier | C10: Expression | D10: 2 | E10: Actif
A11: Logiciel métier | B11: crm immobilier | C11: Exact | D11: 2 | E11: Actif
A12: Logiciel métier | B12: crm immobilier | C12: Expression | D12: 2 | E12: Actif
A13: Logiciel métier | B13: crm agent immobilier | C13: Exact | D13: 2 | E13: Actif
A14: Logiciel métier | B14: crm agent immobilier | C14: Expression | D14: 2 | E14: Actif
A15: Logiciel métier | B15: logiciel immobilier indépendant | C15: Exact | D15: 2 | E15: Actif
A16: Logiciel métier | B16: logiciel immobilier indépendant | C16: Expression | D16: 2 | E16: Actif
... A53: Marque | B53: leadengine ai | C53: Exact | D53: 0.5 | E53: Actif
A55: Note | B55: CPC max de départ = HYPOTHÈSE prudente ; ajuste selon le « CPC moyen » réel après 1 semaine. Marque = campagne séparée à petit budget. « chatgpt agent immobilier » : l'annonce ne doit pas laisser entendre que LIMO inclut ChatGPT.

Sheet Exclusions
A1: Mots-clés négatifs — niveau campagne (requête large négative)
A3: Mot-clé négatif | B3: Raison
A4: emploi | B4: Chercheurs d'emploi
A5: recrutement | B5: Chercheurs d'emploi
A6: salaire | B6: Chercheurs d'emploi
A7: devenir | B7: « devenir agent immobilier »
A8: formation | B8: Futurs agents, pas clients
A9: stage | B9: Étudiants
A10: cpf | B10: Formation
A11: bts | B11: Études
A12: diplôme | B12: Études
A13: école | B13: Études
A14: location | B14: Particuliers locataires
... A27: gestion locative | B27: Hors cible (à revoir si LIMO l'adresse)
A29: Chaque semaine : Google Ads → Mots-clés → Termes de recherche → ajouter ici tout terme hors sujet.
